Gill_stt/__init__.py
GILL_STT-0.1.dist-info/METADATA
GILL_STT-0.1.dist-info/WHEEL
GILL_STT-0.1.dist-info/top_level.txt
GILL_STT-0.1.dist-info/RECORD
