Metadata-Version: 2.1
Name: GILL-STT
Version: 0.1
Summary: This is speech to text package
Author: Navi Gill
